{
    "19012": "S05379_y.fits",
    "19019": "S05386_y.fits",
    "16643": "S02865_y.fits",
    "16646": "S02868_y.fits",
    "17328": "S03679_y.fits",
    "17337": "S03688_y.fits",
    "18947": "S05313_y.fits",
    "18949": "S05315_y.fits",
    "62330": "DRP0174_x.fits",
    "62343": "DRP0187_x.fits",
    "63438": "DR01413_y.fits",
    "63440": "DR01415_y.fits",
    "9528": "GS00987_x.fits",
    "9553": "GS01012_x.fits",
    "9313": "GS00762_x.fits",
    "9315": "GS00764_x.fits",
    "9316": "GS00765_x.fits",
    "9317": "GS00766_x.fits",
    "9318": "GS00767_x.fits",
    "9319": "GS00768_x.fits",
    "9320": "GS00769_x.fits",
    "9321": "GS00770_x.fits",
    "9322": "GS00771_x.fits",
    "9323": "GS00772_x.fits",
    "9324": "GS00773_x.fits",
    "9325": "GS00774_x.fits",
    "9326": "GS00775_x.fits",
    "9327": "GS00776_x.fits",
    "9328": "GS00777_x.fits",
    "9344": "GS00783_x.fits",
    "9345": "GS00784_x.fits",
    "9346": "GS00785_x.fits",
    "9347": "GS00786_x.fits",
    "9348": "GS00787_x.fits",
    "9349": "GS00788_x.fits",
    "9350": "GS00789_x.fits",
    "9534": "GS00993_x.fits",
    "9535": "GS00994_x.fits"
}